accounts/models.py
accounts/apps.py
accounts/signals.py
accounts/admin.py
accounts/views.py
accounts/serializers.py
accounts/urls.py
accounts/authentication.py
accounts/__init__.py
accounts/tests/tests_views.py
accounts/tests/factory.pyc
accounts/tests/tests_views.pyc
accounts/tests/tests_models.py
accounts/tests/tests_models.pyc
accounts/tests/tests_authentication.py
accounts/tests/__init__.pyc
accounts/tests/factory.py
accounts/tests/tests_authentication.pyc
accounts/tests/__init__.py
accounts/tests/__pycache__/factory.cpython-34.pyc
accounts/tests/__pycache__/tests_models.cpython-34.pyc
accounts/tests/__pycache__/test_authentication.cpython-34.pyc
accounts/tests/__pycache__/tests_views.cpython-34.pyc
accounts/tests/__pycache__/tests_authentication.cpython-34.pyc
accounts/tests/__pycache__/__init__.cpython-34.pyc
djangorf_accounts-1.0.dist-info/top_level.txt
djangorf_accounts-1.0.dist-info/WHEEL
djangorf_accounts-1.0.dist-info/metadata.json
djangorf_accounts-1.0.dist-info/RECORD
djangorf_accounts-1.0.dist-info/METADATA
djangorf_accounts-1.0.dist-info/DESCRIPTION.rst
