Metadata-Version: 2.0
Name: djangorf-accounts
Version: 1.0
Summary: App de Django para manejar cuentas utilizando tokens.
Home-page: UNKNOWN
Author: Marco Antonio Sanchez Santos
Author-email: m@dfrog.uno
License: MIT License
Platform: UNKNOWN
Classifier: Environment :: Web Environment
Classifier: Framework :: Django
Classifier: Intended Audience :: Developers
Classifier: License :: OSI Approved :: MIT License
Classifier: Operating System :: OS Independent
Classifier: Programming Language :: Python
Classifier: Programming Language :: Python :: 3
Classifier: Topic :: Internet :: WWW/HTTP
Classifier: Topic :: Internet :: WWW/HTTP :: Dynamic Content
